{"version": 0.6, "generator": "Overpass API 0.7.62.11 87bfad18", "osm3s": {"timestamp_osm_base": "2026-04-29T17:36:45Z", "copyright": "The data included in this document is from www.openstreetmap.org. The data is made available under ODbL."}, "elements": [{"type": "node", "id": 97410688, "lat": -9.7794378, "lon": 23.1354904}, {"type": "node", "id": 97410689, "lat": -9.781192, "lon": 23.1363843}, {"type": "node", "id": 97410690, "lat": -9.809413, "lon": 23.1449618}, {"type": "node", "id": 97410691, "lat": -9.8123083, "lon": 23.146427}, {"type": "node", "id": 97410692, "lat": -9.8403162, "lon": 23.1618012}, {"type": "node", "id": 97410693, "lat": -9.8553078, "lon": 23.1754026}, {"type": "node", "id": 97410694, "lat": -9.8688808, "lon": 23.1923613}, {"type": "node", "id": 97410695, "lat": -9.8690631, "lon": 23.2036507}, {"type": "node", "id": 97410699, "lat": -9.8674035, "lon": 23.2292389}, {"type": "node", "id": 97410704, "lat": -9.9011099, "lon": 23.3278047}, {"type": "node", "id": 97410706, "lat": -9.9168258, "lon": 23.3488896}, {"type": "node", "id": 97410709, "lat": -9.9118797, "lon": 23.3665252}, {"type": "node", "id": 97410713, "lat": -9.9038765, "lon": 23.4351898}, {"type": "node", "id": 97410714, "lat": -9.9074844, "lon": 23.4439082}, {"type": "node", "id": 380941751, "lat": -10.1009305, "lon": 23.5091249}, {"type": "node", "id": 381240602, "lat": -10.0982212, "lon": 23.3276921}, {"type": "node", "id": 381249007, "lat": -10.1287194, "lon": 23.5289168}, {"type": "node", "id": 381333109, "lat": -10.0928448, "lon": 23.3437961}, {"type": "node", "id": 381351109, "lat": -10.1221215, "lon": 23.4695649}, {"type": "node", "id": 381396476, "lat": -10.1136725, "lon": 23.2728342}, {"type": "node", "id": 382067527, "lat": -10.1047594, "lon": 23.1468415}, {"type": "node", "id": 382081484, "lat": -10.1030615, "lon": 23.409116}, {"type": "node", "id": 382099457, "lat": -10.1051132, "lon": 23.1497329}, {"type": "node", "id": 382103416, "lat": -10.1330602, "lon": 23.5133332}, {"type": "node", "id": 382104160, "lat": -10.1067293, "lon": 23.425287}, {"type": "node", "id": 382114657, "lat": -10.0933307, "lon": 23.3395475}, {"type": "node", "id": 382122684, "lat": -10.1205974, "lon": 23.2191619}, {"type": "node", "id": 382126961, "lat": -10.1255825, "lon": 23.5473168}, {"type": "node", "id": 382127496, "lat": -10.1238979, "lon": 23.2550123}, {"type": "node", "id": 382128922, "lat": -10.1262479, "lon": 23.2473654}, {"type": "node", "id": 382141044, "lat": -10.0967794, "lon": 23.3838201}, {"type": "node", "id": 382155958, "lat": -10.0993197, "lon": 23.3231592}, {"type": "node", "id": 382158118, "lat": -10.1317532, "lon": 23.4893596}, {"type": "node", "id": 382184253, "lat": -10.1096603, "lon": 23.4418872}, {"type": "node", "id": 382188149, "lat": -10.1009199, "lon": 23.2986706}, {"type": "node", "id": 382197047, "lat": -10.1356613, "lon": 23.5088271}, {"type": "node", "id": 382446088, "lat": -10.1026944, "lon": 23.4043014}, {"type": "node", "id": 382446854, "lat": -10.1203122, "lon": 23.2141489}, {"type": "node", "id": 382447916, "lat": -10.1300237, "lon": 23.5264438}, {"type": "node", "id": 382449537, "lat": -10.0952056, "lon": 23.3608898}, {"type": "node", "id": 382459243, "lat": -10.1132462, "lon": 23.2754105}, {"type": "node", "id": 382463373, "lat": -10.0997894, "lon": 23.3180449}, {"type": "node", "id": 382474886, "lat": -10.1093118, "lon": 23.1671941}, {"type": "node", "id": 382476148, "lat": -10.1033916, "lon": 23.1408709}, {"type": "node", "id": 382484793, "lat": -10.1246742, "lon": 23.2532796}, {"type": "node", "id": 382486670, "lat": -10.1319565, "lon": 23.5228175}, {"type": "node", "id": 382493441, "lat": -10.123185, "lon": 23.4728292}, {"type": "node", "id": 382494580, "lat": -10.1222688, "lon": 23.223837}, {"type": "node", "id": 382759310, "lat": -10.1050076, "lon": 23.1543195}, {"type": "node", "id": 382774935, "lat": -10.1021082, "lon": 23.1353456}, {"type": "node", "id": 382793318, "lat": -10.0956967, "lon": 23.3680487}, {"type": "node", "id": 383608419, "lat": -10.1184639, "lon": 23.2040316}, {"type": "node", "id": 383610588, "lat": -10.1145348, "lon": 23.2680586}, {"type": "node", "id": 383677077, "lat": -10.1235151, "lon": 23.4756696}, {"type": "node", "id": 383684582, "lat": -10.1279985, "lon": 23.4846416}, {"type": "node", "id": 383718087, "lat": -10.0933439, "lon": 23.3469799}, {"type": "node", "id": 383781997, "lat": -10.0954802, "lon": 23.3794856}, {"type": "node", "id": 383798488, "lat": -10.1055938, "lon": 23.1579888}, {"type": "node", "id": 383810869, "lat": -10.09604, "lon": 23.3329546}, {"type": "node", "id": 383811255, "lat": -10.1136238, "lon": 23.1770512}, {"type": "node", "id": 383829057, "lat": -10.0993514, "lon": 23.3015192}, {"type": "node", "id": 383844301, "lat": -10.1106347, "lon": 23.447139}, {"type": "node", "id": 383863480, "lat": -10.1333471, "lon": 23.5179448}, {"type": "node", "id": 383865138, "lat": -10.1253819, "lon": 23.5522896}, {"type": "node", "id": 435261665, "lat": -10.079226, "lon": 23.0911088}, {"type": "node", "id": 435274224, "lat": -9.930097, "lon": 23.4733173}, {"type": "node", "id": 435274395, "lat": -10.0868619, "lon": 23.1124447}, {"type": "node", "id": 435274897, "lat": -9.9504404, "lon": 23.4710432}, {"type": "node", "id": 435300862, "lat": -10.0850696, "lon": 23.1033458}, {"type": "node", "id": 435316858, "lat": -10.1071571, "lon": 23.1627899}, {"type": "node", "id": 435319011, "lat": -10.1163013, "lon": 23.4583747}, {"type": "node", "id": 435331923, "lat": -10.0402491, "lon": 23.0408658}, {"type": "node", "id": 435341614, "lat": -10.1090768, "lon": 23.4339774}, {"type": "node", "id": 435346556, "lat": -10.1258255, "lon": 23.5450369}, {"type": "node", "id": 435351018, "lat": -10.1108539, "lon": 23.2802761}, {"type": "node", "id": 435354074, "lat": -10.100346, "lon": 23.1257283}, {"type": "node", "id": 435359293, "lat": -10.098987, "lon": 23.3906007}, {"type": "node", "id": 435362649, "lat": -10.1184639, "lon": 23.4623873}, {"type": "node", "id": 435376772, "lat": -10.1263826, "lon": 23.2352471}, {"type": "node", "id": 435377244, "lat": -10.1322628, "lon": 23.4923691}, {"type": "node", "id": 435377296, "lat": -10.1004129, "lon": 23.3117062}, {"type": "node", "id": 435387835, "lat": -9.9661189, "lon": 23.4627678}, {"type": "node", "id": 435432691, "lat": -10.0988338, "lon": 23.3048934}, {"type": "node", "id": 435458011, "lat": -10.100714, "lon": 23.3971131}, {"type": "node", "id": 435467162, "lat": -10.0841073, "lon": 23.0994806}, {"type": "node", "id": 435470382, "lat": -10.0905426, "lon": 23.1155808}, {"type": "node", "id": 435470557, "lat": -10.1214714, "lon": 23.2217208}, {"type": "node", "id": 435473548, "lat": -9.9542072, "lon": 23.4690922}, {"type": "node", "id": 435474372, "lat": -10.1304911, "lon": 23.4876323}, {"type": "node", "id": 435478458, "lat": -10.1254928, "lon": 23.5413033}, {"type": "node", "id": 435486093, "lat": -10.045034, "lon": 23.0550414}, {"type": "node", "id": 435490387, "lat": -10.1193326, "lon": 23.2098198}, {"type": "node", "id": 435493709, "lat": -10.1153188, "lon": 23.4556973}, {"type": "node", "id": 435526326, "lat": -10.0412699, "lon": 23.045309}, {"type": "node", "id": 435528085, "lat": -10.1021241, "lon": 23.4011418}, {"type": "node", "id": 435528646, "lat": -10.1049839, "lon": 23.4187263}, {"type": "node", "id": 435538570, "lat": -10.1253713, "lon": 23.549763}, {"type": "node", "id": 435543947, "lat": -10.0762891, "lon": 23.0873554}, {"type": "node", "id": 435546520, "lat": -10.0862682, "lon": 23.1088308}, {"type": "node", "id": 435551240, "lat": -9.8322746, "lon": 23.1573567}, {"type": "node", "id": 435576795, "lat": -10.0638101, "lon": 23.0708443}, {"type": "node", "id": 435594225, "lat": -10.1249541, "lon": 23.2266024}, {"type": "node", "id": 435603811, "lat": -10.0690605, "lon": 23.0794668}, {"type": "node", "id": 435624886, "lat": -10.0726152, "lon": 23.0830995}, {"type": "node", "id": 435641950, "lat": -10.1255192, "lon": 23.539179}, {"type": "node", "id": 435647091, "lat": -10.0967433, "lon": 23.3302211}, {"type": "node", "id": 435660840, "lat": -10.0800769, "lon": 23.093106}, {"type": "node", "id": 435664232, "lat": -10.0260871, "lon": 23.4628384}, {"type": "node", "id": 435676243, "lat": -10.1127999, "lon": 23.4523264}, {"type": "node", "id": 435677433, "lat": -10.0959525, "lon": 23.1183548}, {"type": "node", "id": 435691989, "lat": -9.9281207, "lon": 23.4699833}, {"type": "node", "id": 435697397, "lat": -10.1110387, "lon": 23.4491613}, {"type": "node", "id": 435722928, "lat": -10.1097237, "lon": 23.4396476}, {"type": "node", "id": 435740918, "lat": -10.0285254, "lon": 23.4662873}, {"type": "node", "id": 435741299, "lat": -10.0657698, "lon": 23.0730974}, {"type": "node", "id": 435742067, "lat": -9.8782794, "lon": 23.2759672}, {"type": "node", "id": 435746596, "lat": -10.067229, "lon": 23.0764676}, {"type": "node", "id": 435748221, "lat": -10.0546395, "lon": 23.503975}, {"type": "node", "id": 435751980, "lat": -9.9136738, "lon": 23.3915904}, {"type": "node", "id": 435756911, "lat": -10.0374091, "lon": 23.5001093}, {"type": "node", "id": 435763861, "lat": -10.0276736, "lon": 23.463892}, {"type": "node", "id": 435778101, "lat": -9.9118163, "lon": 23.3721846}, {"type": "node", "id": 435783438, "lat": -10.0361268, "lon": 23.4870596}, {"type": "node", "id": 435783712, "lat": -9.9136975, "lon": 23.361842}, {"type": "node", "id": 435784033, "lat": -9.9234311, "lon": 23.4653887}, {"type": "node", "id": 435792977, "lat": -10.0947144, "lon": 23.3358675}, {"type": "node", "id": 435794869, "lat": -10.0817849, "lon": 23.0961046}, {"type": "node", "id": 435798739, "lat": -9.9108625, "lon": 23.4512159}, {"type": "node", "id": 435800629, "lat": -9.9180492, "lon": 23.4611803}, {"type": "node", "id": 435802167, "lat": -10.0205712, "lon": 23.4629881}, {"type": "node", "id": 435819852, "lat": -10.0505802, "lon": 23.5050666}, {"type": "node", "id": 435822576, "lat": -9.9581101, "lon": 23.4668628}, {"type": "node", "id": 435825380, "lat": -10.0956598, "lon": 23.3727586}, {"type": "node", "id": 435832384, "lat": -10.0772563, "lon": 23.509275}, {"type": "node", "id": 435834403, "lat": -10.114981, "lon": 23.1830353}, {"type": "node", "id": 435836898, "lat": -10.111081, "lon": 23.170968}, {"type": "node", "id": 435837417, "lat": -10.0464998, "lon": 23.5049379}, {"type": "node", "id": 435840161, "lat": -9.9148575, "lon": 23.4584177}, {"type": "node", "id": 435840219, "lat": -10.1021585, "lon": 23.1315911}, {"type": "node", "id": 435840285, "lat": -10.0949917, "lon": 23.356829}, {"type": "node", "id": 435847670, "lat": -9.9454406, "lon": 23.4720385}, {"type": "node", "id": 435848095, "lat": -10.1063332, "lon": 23.292743}, {"type": "node", "id": 435852897, "lat": -9.9131585, "lon": 23.4555343}, {"type": "node", "id": 435861857, "lat": -10.0505465, "lon": 23.0612999}, {"type": "node", "id": 435886250, "lat": -9.9166911, "lon": 23.3527118}, {"type": "node", "id": 435889717, "lat": -10.1268658, "lon": 23.5324413}, {"type": "node", "id": 435890315, "lat": -10.1261133, "lon": 23.229754}, {"type": "node", "id": 435895051, "lat": -10.1494626, "lon": 23.5087685}, {"type": "node", "id": 435899080, "lat": -9.9150819, "lon": 23.3462905}, {"type": "node", "id": 435900021, "lat": -10.2190939, "lon": 23.5083287}, {"type": "node", "id": 435906539, "lat": -10.2631986, "lon": 23.507601}, {"type": "node", "id": 435911614, "lat": -10.2868507, "lon": 23.4975322}, {"type": "node", "id": 435915735, "lat": -9.9785508, "lon": 23.4640825}, {"type": "node", "id": 435929759, "lat": -10.1004577, "lon": 23.3107058}, {"type": "node", "id": 435939510, "lat": -9.9349213, "lon": 23.4738645}, {"type": "node", "id": 435941937, "lat": -10.0558214, "lon": 23.0660634}, {"type": "node", "id": 435951037, "lat": -9.7673908, "lon": 23.1238915}, {"type": "node", "id": 435951598, "lat": -10.1208693, "lon": 23.4668961}, {"type": "node", "id": 435956762, "lat": -10.1165284, "lon": 23.2646254}, {"type": "node", "id": 435976833, "lat": -10.1205419, "lon": 23.217448}, {"type": "node", "id": 435977775, "lat": -10.0527522, "lon": 23.0636789}, {"type": "node", "id": 435991931, "lat": -10.0477325, "lon": 23.0575479}, {"type": "node", "id": 435992689, "lat": -10.1251363, "lon": 23.2512224}, {"type": "node", "id": 435999527, "lat": -10.1266651, "lon": 23.5356545}, {"type": "node", "id": 436004445, "lat": -10.1247561, "lon": 23.4793201}, {"type": "node", "id": 436017553, "lat": -10.1070242, "lon": 23.288845}, {"type": "node", "id": 436017972, "lat": -9.8672134, "lon": 23.2199907}, {"type": "node", "id": 436022886, "lat": -9.8735235, "lon": 23.2651913}, {"type": "node", "id": 436028211, "lat": -9.8952018, "lon": 23.3145117}, {"type": "node", "id": 436032890, "lat": -10.0622135, "lon": 23.0697138}, {"type": "node", "id": 436044015, "lat": -10.1182658, "lon": 23.1954619}, {"type": "node", "id": 436044948, "lat": -10.1191266, "lon": 23.1996623}, {"type": "node", "id": 436045125, "lat": -10.1270453, "lon": 23.2434198}, {"type": "node", "id": 436062697, "lat": -9.9719995, "lon": 23.4634924}, {"type": "node", "id": 436063202, "lat": -10.0404864, "lon": 23.0386249}, {"type": "node", "id": 436065796, "lat": -9.9633611, "lon": 23.4638411}, {"type": "node", "id": 436066660, "lat": -10.093012, "lon": 23.1152235}, {"type": "node", "id": 436070104, "lat": -10.059263, "lon": 23.0680769}, {"type": "node", "id": 436070452, "lat": -10.0998122, "lon": 23.3148088}, {"type": "node", "id": 436083700, "lat": -10.097782, "lon": 23.1216034}, {"type": "node", "id": 436087113, "lat": -10.1040623, "lon": 23.2951462}, {"type": "node", "id": 436087644, "lat": -9.8692004, "lon": 23.2407295}, {"type": "node", "id": 436104387, "lat": -10.0427264, "lon": 23.0491768}, {"type": "node", "id": 2275430032, "lat": -9.76505, "lon": 23.1216106}, {"type": "node", "id": 2275430051, "lat": -9.7735607, "lon": 23.129952}, {"type": "node", "id": 2275430105, "lat": -9.834393, "lon": 23.1585692}, {"type": "node", "id": 2275430114, "lat": -9.8469403, "lon": 23.1653194}, {"type": "node", "id": 2275430118, "lat": -9.8481592, "lon": 23.1664441}, {"type": "node", "id": 2275430119, "lat": -9.8698263, "lon": 23.1944496}, {"type": "node", "id": 2671728711, "lat": -10.0369502, "lon": 23.4981522}, {"type": "node", "id": 4697407617, "lat": -10.3017934, "lon": 23.4912028}, {"type": "node", "id": 4697407618, "lat": -10.2980814, "lon": 23.4927664}, {"type": "node", "id": 4697407619, "lat": -10.2938654, "lon": 23.4945438}, {"type": "node", "id": 4697407620, "lat": -10.2904741, "lon": 23.4960014}, {"type": "node", "id": 4697407621, "lat": -10.2877861, "lon": 23.4971462}, {"type": "node", "id": 4697407622, "lat": -10.2848812, "lon": 23.4983729}, {"type": "node", "id": 4697407623, "lat": -10.279805, "lon": 23.5005258}, {"type": "node", "id": 4697407624, "lat": -10.2762608, "lon": 23.5020371}, {"type": "node", "id": 4697407625, "lat": -10.2747461, "lon": 23.5026726}, {"type": "node", "id": 4697407626, "lat": -10.2734126, "lon": 23.5032706}, {"type": "node", "id": 4697407627, "lat": -10.271604, "lon": 23.5040185}, {"type": "node", "id": 4697407628, "lat": -10.2684002, "lon": 23.5053656}, {"type": "node", "id": 4697407629, "lat": -10.2671784, "lon": 23.5059018}, {"type": "node", "id": 4697407630, "lat": -10.2651185, "lon": 23.5067738}, {"type": "node", "id": 4697407631, "lat": -10.2639965, "lon": 23.5072382}, {"type": "node", "id": 4697407632, "lat": -10.2614555, "lon": 23.5080052}, {"type": "node", "id": 4697407633, "lat": -10.2623551, "lon": 23.5078234}, {"type": "node", "id": 4697407634, "lat": -10.2596353, "lon": 23.5080467}, {"type": "node", "id": 4697407635, "lat": -10.2553428, "lon": 23.5080389}, {"type": "node", "id": 4697407636, "lat": -10.2486778, "lon": 23.5080956}, {"type": "node", "id": 4697428333, "lat": -10.2339117, "lon": 23.5081994}, {"type": "node", "id": 4983388667, "lat": -10.1028634, "lon": 23.1384945}, {"type": "node", "id": 4983388668, "lat": -10.1025783, "lon": 23.1374913}, {"type": "node", "id": 4983388669, "lat": -10.1037507, "lon": 23.1420457}, {"type": "node", "id": 4983388670, "lat": -10.1044478, "lon": 23.1458008}, {"type": "node", "id": 4983388671, "lat": -10.1051555, "lon": 23.1486386}, {"type": "node", "id": 4983388672, "lat": -10.1050287, "lon": 23.1476837}, {"type": "node", "id": 4983388673, "lat": -10.1048967, "lon": 23.1529838}, {"type": "node", "id": 4983388674, "lat": -10.1049707, "lon": 23.1520182}, {"type": "node", "id": 4983388675, "lat": -10.1052347, "lon": 23.1564707}, {"type": "node", "id": 4983388676, "lat": -10.1065339, "lon": 23.1603304}, {"type": "node", "id": 4983388677, "lat": -10.1060823, "lon": 23.1589946}, {"type": "node", "id": 4983388678, "lat": -10.1075848, "lon": 23.1644851}, {"type": "node", "id": 4983388679, "lat": -10.1101462, "lon": 23.1682938}, {"type": "node", "id": 4983388680, "lat": -10.1083559, "lon": 23.1657565}, {"type": "node", "id": 4983388681, "lat": -10.1114031, "lon": 23.1720784}, {"type": "node", "id": 4983388682, "lat": -10.1116091, "lon": 23.1729743}, {"type": "node", "id": 4983388683, "lat": -10.1119048, "lon": 23.1737789}, {"type": "node", "id": 4983388684, "lat": -10.1132515, "lon": 23.1762144}, {"type": "node", "id": 4983388685, "lat": -10.1126917, "lon": 23.1752622}, {"type": "node", "id": 4983388686, "lat": -10.114416, "lon": 23.1799453}, {"type": "node", "id": 4983388687, "lat": -10.1149414, "lon": 23.181501}, {"type": "node", "id": 4983388688, "lat": -10.1156913, "lon": 23.1853875}, {"type": "node", "id": 4983388689, "lat": -10.1154484, "lon": 23.1847063}, {"type": "node", "id": 4983388690, "lat": -10.1161191, "lon": 23.1873643}, {"type": "node", "id": 4983388691, "lat": -10.1159501, "lon": 23.1865382}, {"type": "node", "id": 4983388692, "lat": -10.116832, "lon": 23.1894296}, {"type": "node", "id": 4983388693, "lat": -10.1163937, "lon": 23.1882656}, {"type": "node", "id": 4983388694, "lat": -10.1175951, "lon": 23.1923398}, {"type": "node", "id": 4983388695, "lat": -10.1190791, "lon": 23.1985438}, {"type": "node", "id": 4983388696, "lat": -10.1187385, "lon": 23.2023445}, {"type": "node", "id": 4983388697, "lat": -10.1189761, "lon": 23.2073736}, {"type": "node", "id": 4983388698, "lat": -10.1184771, "lon": 23.2046673}, {"type": "node", "id": 4983388699, "lat": -10.1187886, "lon": 23.2057911}, {"type": "node", "id": 4983388700, "lat": -10.1202092, "lon": 23.2129124}, {"type": "node", "id": 4983388701, "lat": -10.1198976, "lon": 23.2112923}, {"type": "node", "id": 4983388702, "lat": -10.1191055, "lon": 23.2087845}, {"type": "node", "id": 4983388703, "lat": -10.1210753, "lon": 23.2204172}, {"type": "node", "id": 4983388704, "lat": -10.125271, "lon": 23.2268813}, {"type": "node", "id": 4983388705, "lat": -10.1242623, "lon": 23.2258889}, {"type": "node", "id": 4983388706, "lat": -10.1255139, "lon": 23.2272541}, {"type": "node", "id": 4983388707, "lat": -10.1259839, "lon": 23.2284826}, {"type": "node", "id": 4983388708, "lat": -10.12624, "lon": 23.2327849}, {"type": "node", "id": 4983388709, "lat": -10.1266308, "lon": 23.2383853}, {"type": "node", "id": 4983388710, "lat": -10.1269265, "lon": 23.2414377}, {"type": "node", "id": 4983388711, "lat": -10.1270744, "lon": 23.242709}, {"type": "node", "id": 4983388712, "lat": -10.1269107, "lon": 23.2448012}, {"type": "node", "id": 4983388713, "lat": -10.1266361, "lon": 23.2460135}, {"type": "node", "id": 4983388714, "lat": -10.1257542, "lon": 23.2488781}, {"type": "node", "id": 4983388715, "lat": -10.1245079, "lon": 23.2539636}, {"type": "node", "id": 4983388716, "lat": -10.1226464, "lon": 23.2571071}, {"type": "node", "id": 4983388717, "lat": -10.1212971, "lon": 23.2588372}, {"type": "node", "id": 4983388718, "lat": -10.1196706, "lon": 23.2609159}, {"type": "node", "id": 4983388719, "lat": -10.1182896, "lon": 23.2626003}, {"type": "node", "id": 4983388720, "lat": -10.11482, "lon": 23.2669079}, {"type": "node", "id": 4983389121, "lat": -10.1149995, "lon": 23.2664654}, {"type": "node", "id": 4983389122, "lat": -10.1153349, "lon": 23.2659772}, {"type": "node", "id": 4983389123, "lat": -10.1142496, "lon": 23.2693058}, {"type": "node", "id": 4983389124, "lat": -10.1112764, "lon": 23.2794285}, {"type": "node", "id": 4983389125, "lat": -10.1122375, "lon": 23.2783717}, {"type": "node", "id": 4983389126, "lat": -10.1126019, "lon": 23.2775348}, {"type": "node", "id": 4983389127, "lat": -10.0988497, "lon": 23.303681}, {"type": "node", "id": 4983389128, "lat": -10.0996155, "lon": 23.3007145}, {"type": "node", "id": 4983389129, "lat": -10.0999799, "lon": 23.2999742}, {"type": "node", "id": 4983389130, "lat": -10.0999746, "lon": 23.3082515}, {"type": "node", "id": 4983389131, "lat": -10.1003654, "lon": 23.309437}, {"type": "node", "id": 4983389132, "lat": -10.099457, "lon": 23.3072323}, {"type": "node", "id": 4983389133, "lat": -10.0988919, "lon": 23.305816}, {"type": "node", "id": 4983389134, "lat": -10.0999323, "lon": 23.3140236}, {"type": "node", "id": 4983389135, "lat": -10.0985117, "lon": 23.3271503}, {"type": "node", "id": 4983389136, "lat": -10.0988444, "lon": 23.3256698}, {"type": "node", "id": 4983389137, "lat": -10.0996049, "lon": 23.321448}, {"type": "node", "id": 4983389138, "lat": -10.0997475, "lon": 23.3197582}, {"type": "node", "id": 4983389139, "lat": -10.0976719, "lon": 23.3287919}, {"type": "node", "id": 4983389140, "lat": -10.0962565, "lon": 23.3323055}, {"type": "node", "id": 4983389141, "lat": -10.096584, "lon": 23.3306211}, {"type": "node", "id": 4983389142, "lat": -10.0940542, "lon": 23.3371174}, {"type": "node", "id": 4983389143, "lat": -10.0928765, "lon": 23.3413231}, {"type": "node", "id": 4983389144, "lat": -10.0929398, "lon": 23.3450407}, {"type": "node", "id": 4983389145, "lat": -10.0938747, "lon": 23.3493108}, {"type": "node", "id": 4983389146, "lat": -10.0947091, "lon": 23.3523363}, {"type": "node", "id": 4983389147, "lat": -10.0944002, "lon": 23.3510998}, {"type": "node", "id": 4983389148, "lat": -10.0947144, "lon": 23.3532965}, {"type": "node", "id": 4983389149, "lat": -10.0948755, "lon": 23.3549139}, {"type": "node", "id": 4983389150, "lat": -10.0949362, "lon": 23.3589292}, {"type": "node", "id": 4983389151, "lat": -10.0956017, "lon": 23.3654898}, {"type": "node", "id": 4983389152, "lat": -10.0952953, "lon": 23.3627218}, {"type": "node", "id": 4983389153, "lat": -10.0975346, "lon": 23.3860034}, {"type": "node", "id": 4983389154, "lat": -10.0957284, "lon": 23.3807731}, {"type": "node", "id": 4983389155, "lat": -10.0955594, "lon": 23.377254}, {"type": "node", "id": 4983389156, "lat": -10.0958763, "lon": 23.3700281}, {"type": "node", "id": 4983389157, "lat": -10.0998531, "lon": 23.394168}, {"type": "node", "id": 4983389158, "lat": -10.1001806, "lon": 23.3959275}, {"type": "node", "id": 4983389159, "lat": -10.1011523, "lon": 23.3978534}, {"type": "node", "id": 4983389160, "lat": -10.1015114, "lon": 23.3990282}, {"type": "node", "id": 4983389161, "lat": -10.1022931, "lon": 23.4064203}, {"type": "node", "id": 4983389162, "lat": -10.1022403, "lon": 23.4058946}, {"type": "node", "id": 4983389163, "lat": -10.1023459, "lon": 23.4051275}, {"type": "node", "id": 4983389164, "lat": -10.1026575, "lon": 23.4026653}, {"type": "node", "id": 4983389165, "lat": -10.1027842, "lon": 23.4038562}, {"type": "node", "id": 4983389166, "lat": -10.102602, "lon": 23.407461}, {"type": "node", "id": 4983389167, "lat": -10.1034682, "lon": 23.4131473}, {"type": "node", "id": 4983389168, "lat": -10.1033889, "lon": 23.4119484}, {"type": "node", "id": 4983389169, "lat": -10.1037507, "lon": 23.4140539}, {"type": "node", "id": 4983389170, "lat": -10.10463, "lon": 23.417801}, {"type": "node", "id": 4983389171, "lat": -10.1043501, "lon": 23.4167978}, {"type": "node", "id": 4983389172, "lat": -10.1056651, "lon": 23.4214085}, {"type": "node", "id": 4983389173, "lat": -10.1061246, "lon": 23.4236938}, {"type": "node", "id": 4983389174, "lat": -10.1072917, "lon": 23.4275883}, {"type": "node", "id": 4983389175, "lat": -10.1076271, "lon": 23.4289402}, {"type": "node", "id": 4983389176, "lat": -10.1090688, "lon": 23.4324968}, {"type": "node", "id": 4983389177, "lat": -10.1088946, "lon": 23.4320864}, {"type": "node", "id": 4983389178, "lat": -10.1080918, "lon": 23.4306514}, {"type": "node", "id": 4983389179, "lat": -10.1090424, "lon": 23.434833}, {"type": "node", "id": 4983389180, "lat": -10.1090108, "lon": 23.4343797}, {"type": "node", "id": 4983389181, "lat": -10.1092695, "lon": 23.433331}, {"type": "node", "id": 4983389182, "lat": -10.1091692, "lon": 23.433634}, {"type": "node", "id": 4983389183, "lat": -10.1091982, "lon": 23.432875}, {"type": "node", "id": 4983389184, "lat": -10.1092088, "lon": 23.4358254}, {"type": "node", "id": 4983389185, "lat": -10.1097105, "lon": 23.4382528}, {"type": "node", "id": 4983389186, "lat": -10.1100828, "lon": 23.4445077}, {"type": "node", "id": 4983389187, "lat": -10.1112499, "lon": 23.4497085}, {"type": "node", "id": 4983389188, "lat": -10.1117569, "lon": 23.450835}, {"type": "node", "id": 4983389189, "lat": -10.1121108, "lon": 23.451452}, {"type": "node", "id": 4983389190, "lat": -10.1137268, "lon": 23.4530452}, {"type": "node", "id": 4983389191, "lat": -10.1147935, "lon": 23.4544668}, {"type": "node", "id": 4983389192, "lat": -10.1146404, "lon": 23.4541261}, {"type": "node", "id": 4983389193, "lat": -10.1142971, "lon": 23.4536353}, {"type": "node", "id": 4983389194, "lat": -10.1151104, "lon": 23.4553331}, {"type": "node", "id": 4983389195, "lat": -10.1149467, "lon": 23.4549308}, {"type": "node", "id": 4983389196, "lat": -10.1159475, "lon": 23.4572482}, {"type": "node", "id": 4983389197, "lat": -10.1159158, "lon": 23.4566018}, {"type": "node", "id": 4983389198, "lat": -10.1158392, "lon": 23.4563658}, {"type": "node", "id": 4983389199, "lat": -10.1167687, "lon": 23.4592867}, {"type": "node", "id": 4983389200, "lat": -10.1159871, "lon": 23.457613}, {"type": "node", "id": 4983389201, "lat": -10.1174341, "lon": 23.4605259}, {"type": "node", "id": 4983389202, "lat": -10.117273, "lon": 23.4601155}, {"type": "node", "id": 4983389203, "lat": -10.1180519, "lon": 23.4616712}, {"type": "node", "id": 4983389204, "lat": -10.1175238, "lon": 23.4609336}, {"type": "node", "id": 4983389205, "lat": -10.1192666, "lon": 23.463884}, {"type": "node", "id": 4983389206, "lat": -10.1201696, "lon": 23.4656006}, {"type": "node", "id": 4983389207, "lat": -10.1215242, "lon": 23.4683204}, {"type": "node", "id": 4983389208, "lat": -10.1225645, "lon": 23.4706163}, {"type": "node", "id": 4983389209, "lat": -10.1230187, "lon": 23.4716624}, {"type": "node", "id": 4983389210, "lat": -10.1227916, "lon": 23.4710455}, {"type": "node", "id": 4983389211, "lat": -10.1233963, "lon": 23.4745941}, {"type": "node", "id": 4983389212, "lat": -10.1234385, "lon": 23.4741783}, {"type": "node", "id": 4983389213, "lat": -10.1233698, "lon": 23.4737116}, {"type": "node", "id": 4983389214, "lat": -10.1237237, "lon": 23.4765601}, {"type": "node", "id": 4983389215, "lat": -10.1244551, "lon": 23.4787166}, {"type": "node", "id": 4983389216, "lat": -10.1240564, "lon": 23.4775981}, {"type": "node", "id": 4983389217, "lat": -10.125366, "lon": 23.480334}, {"type": "node", "id": 4983389218, "lat": -10.1258492, "lon": 23.4814659}, {"type": "node", "id": 4983389219, "lat": -10.1275655, "lon": 23.4841052}, {"type": "node", "id": 4983389220, "lat": -10.1271694, "lon": 23.4834561}, {"type": "node", "id": 4983389221, "lat": -10.1296725, "lon": 23.4867418}, {"type": "node", "id": 4983389222, "lat": -10.1311881, "lon": 23.4884477}, {"type": "node", "id": 4983389223, "lat": -10.1320119, "lon": 23.4899175}, {"type": "node", "id": 4983389224, "lat": -10.1321756, "lon": 23.4910092}, {"type": "node", "id": 4983389225, "lat": -10.1322733, "lon": 23.4933266}, {"type": "node", "id": 4983389226, "lat": -10.1321704, "lon": 23.4930181}, {"type": "node", "id": 4983389227, "lat": -10.1321704, "lon": 23.4929001}, {"type": "node", "id": 4983389228, "lat": -10.1322179, "lon": 23.492707}, {"type": "node", "id": 4983389229, "lat": -10.1328384, "lon": 23.4942412}, {"type": "node", "id": 4983389230, "lat": -10.1362286, "lon": 23.5003567}, {"type": "node", "id": 4983389231, "lat": -10.136086, "lon": 23.499198}, {"type": "node", "id": 4983389232, "lat": -10.1361811, "lon": 23.5010004}, {"type": "node", "id": 4983389233, "lat": -10.1361494, "lon": 23.4995681}, {"type": "node", "id": 4983389234, "lat": -10.1359065, "lon": 23.4988975}, {"type": "node", "id": 4983389235, "lat": -10.1350246, "lon": 23.4973741}, {"type": "node", "id": 4983389236, "lat": -10.1358484, "lon": 23.5056031}, {"type": "node", "id": 4983389237, "lat": -10.1361124, "lon": 23.5022664}, {"type": "node", "id": 4983389238, "lat": -10.1347075, "lon": 23.5088418}, {"type": "node", "id": 4983389239, "lat": -10.1253132, "lon": 23.550117}, {"type": "node", "id": 4983389240, "lat": -10.1255086, "lon": 23.5495537}, {"type": "node", "id": 4983389241, "lat": -10.1257357, "lon": 23.5487544}, {"type": "node", "id": 4983389242, "lat": -10.1256037, "lon": 23.5492748}, {"type": "node", "id": 4983389243, "lat": -10.1252657, "lon": 23.5511577}, {"type": "node", "id": 4983389244, "lat": -10.1256353, "lon": 23.5461742}, {"type": "node", "id": 4983389245, "lat": -10.125667, "lon": 23.5434812}, {"type": "node", "id": 4983389246, "lat": -10.1254611, "lon": 23.5398334}, {"type": "node", "id": 4983389247, "lat": -10.1258043, "lon": 23.5377467}, {"type": "node", "id": 4983389248, "lat": -10.1262004, "lon": 23.537001}, {"type": "node", "id": 4983389249, "lat": -10.1265648, "lon": 23.5364485}, {"type": "node", "id": 4983389250, "lat": -10.1267126, "lon": 23.5345924}, {"type": "node", "id": 4983389251, "lat": -10.1267549, "lon": 23.5331494}, {"type": "node", "id": 4983389252, "lat": -10.127283, "lon": 23.5314971}, {"type": "node", "id": 4983389253, "lat": -10.128017, "lon": 23.5308212}, {"type": "node", "id": 4983389254, "lat": -10.1287194, "lon": 23.5292655}, {"type": "node", "id": 4983389255, "lat": -10.1285873, "lon": 23.529582}, {"type": "node", "id": 4983389256, "lat": -10.129427, "lon": 23.5278332}, {"type": "node", "id": 4983389257, "lat": -10.1292105, "lon": 23.5279942}, {"type": "node", "id": 4983389258, "lat": -10.1289253, "lon": 23.5282302}, {"type": "node", "id": 4983389259, "lat": -10.1287933, "lon": 23.5285735}, {"type": "node", "id": 4983389260, "lat": -10.1297016, "lon": 23.5275006}, {"type": "node", "id": 4983389261, "lat": -10.1309109, "lon": 23.5247111}, {"type": "node", "id": 4983389262, "lat": -10.1320251, "lon": 23.5218626}, {"type": "node", "id": 4983389263, "lat": -10.1322575, "lon": 23.5212082}, {"type": "node", "id": 4983389264, "lat": -10.133039, "lon": 23.5192877}, {"type": "node", "id": 4983389265, "lat": -10.1326799, "lon": 23.5203981}, {"type": "node", "id": 4983389266, "lat": -10.1334034, "lon": 23.5166216}, {"type": "node", "id": 4983389267, "lat": -10.1332397, "lon": 23.5151893}, {"type": "node", "id": 4983389268, "lat": -10.1330232, "lon": 23.512668}, {"type": "node", "id": 4983389269, "lat": -10.1331922, "lon": 23.5116702}, {"type": "node", "id": 4983389270, "lat": -10.1332925, "lon": 23.5115415}, {"type": "node", "id": 4983389271, "lat": -10.1336305, "lon": 23.5113645}, {"type": "node", "id": 4983389272, "lat": -10.1339896, "lon": 23.5110211}, {"type": "node", "id": 4983389273, "lat": -10.1343328, "lon": 23.5103345}, {"type": "node", "id": 4983389274, "lat": -10.1347157, "lon": 23.5096827}, {"type": "node", "id": 5813978460, "lat": -9.9508548, "lon": 23.4708524}, {"type": "node", "id": 5813978461, "lat": -9.9496712, "lon": 23.4712762}, {"type": "node", "id": 5813978462, "lat": -9.933278, "lon": 23.4739906}, {"type": "node", "id": 5813978463, "lat": -9.9339781, "lon": 23.4739637}, {"type": "node", "id": 5813978464, "lat": -9.931381, "lon": 23.4739155}, {"type": "node", "id": 5813978465, "lat": -9.9310931, "lon": 23.4739074}, {"type": "node", "id": 5813978466, "lat": -9.9307919, "lon": 23.4738457}, {"type": "node", "id": 5813978467, "lat": -9.9305171, "lon": 23.4737036}, {"type": "node", "id": 5813978468, "lat": -9.9302476, "lon": 23.4734943}, {"type": "node", "id": 5813978469, "lat": -9.9274286, "lon": 23.4689587}, {"type": "node", "id": 5813978470, "lat": -9.9278064, "lon": 23.4694844}, {"type": "node", "id": 5813978471, "lat": -9.9259781, "lon": 23.467395}, {"type": "node", "id": 5813978472, "lat": -9.9257958, "lon": 23.4671723}, {"type": "node", "id": 5813978473, "lat": -9.9221418, "lon": 23.4643963}, {"type": "node", "id": 5813978474, "lat": -9.9156818, "lon": 23.4593806}, {"type": "node", "id": 5813978475, "lat": -9.9162842, "lon": 23.4599063}, {"type": "node", "id": 5813978476, "lat": -9.9170108, "lon": 23.4604374}, {"type": "node", "id": 5813978477, "lat": -9.915053, "lon": 23.4586725}, {"type": "node", "id": 5813978478, "lat": -9.9145562, "lon": 23.4580556}, {"type": "node", "id": 5813978479, "lat": -9.9137187, "lon": 23.4567118}, {"type": "node", "id": 5813978480, "lat": -9.913399, "lon": 23.4559876}, {"type": "node", "id": 5813978481, "lat": -9.9097792, "lon": 23.4491748}, {"type": "node", "id": 5813978482, "lat": -9.9040483, "lon": 23.436225}, {"type": "node", "id": 5813978483, "lat": -9.9039452, "lon": 23.4358844}, {"type": "node", "id": 5813978484, "lat": -9.9038685, "lon": 23.4355545}, {"type": "node", "id": 5813978485, "lat": -9.9039849, "lon": 23.4347391}, {"type": "node", "id": 5813978486, "lat": -9.9040139, "lon": 23.4342617}, {"type": "node", "id": 5813978487, "lat": -9.9040958, "lon": 23.4337816}, {"type": "node", "id": 5813978488, "lat": -9.9043548, "lon": 23.4321428}, {"type": "node", "id": 5813978489, "lat": -9.9048092, "lon": 23.4297073}, {"type": "node", "id": 5813978490, "lat": -9.9050206, "lon": 23.4283554}, {"type": "node", "id": 5813978491, "lat": -9.9053905, "lon": 23.4268105}, {"type": "node", "id": 5813978492, "lat": -9.9063153, "lon": 23.4237957}, {"type": "node", "id": 5813978493, "lat": -9.9136579, "lon": 23.3927813}, {"type": "node", "id": 5813978494, "lat": -9.9137319, "lon": 23.3923709}, {"type": "node", "id": 5813978495, "lat": -9.9137372, "lon": 23.3920652}, {"type": "node", "id": 5813978496, "lat": -9.9134148, "lon": 23.3898282}, {"type": "node", "id": 5813978497, "lat": -9.9129868, "lon": 23.3863145}, {"type": "node", "id": 5813978498, "lat": -9.912572, "lon": 23.3830717}, {"type": "node", "id": 5813978499, "lat": -9.9119934, "lon": 23.3745289}, {"type": "node", "id": 5813978500, "lat": -9.9117582, "lon": 23.3711037}, {"type": "node", "id": 5813978501, "lat": -9.9152538, "lon": 23.3585268}, {"type": "node", "id": 5813978502, "lat": -9.9119273, "lon": 23.3661121}, {"type": "node", "id": 5813978503, "lat": -9.9119696, "lon": 23.3656722}, {"type": "node", "id": 5813978504, "lat": -9.9120066, "lon": 23.3654845}, {"type": "node", "id": 5813978505, "lat": -9.9122021, "lon": 23.3649158}, {"type": "node", "id": 5813978506, "lat": -9.9124399, "lon": 23.3644223}, {"type": "node", "id": 5813978507, "lat": -9.9127358, "lon": 23.3638805}, {"type": "node", "id": 5813978508, "lat": -9.9143264, "lon": 23.3605277}, {"type": "node", "id": 5813978509, "lat": -9.9146804, "lon": 23.3598089}, {"type": "node", "id": 5813978510, "lat": -9.9149288, "lon": 23.3592832}, {"type": "node", "id": 5813978511, "lat": -9.9151666, "lon": 23.3588648}, {"type": "node", "id": 5813978512, "lat": -9.9169606, "lon": 23.351714}, {"type": "node", "id": 5813978513, "lat": -9.9170689, "lon": 23.3512714}, {"type": "node", "id": 5813978514, "lat": -9.9171667, "lon": 23.350845}, {"type": "node", "id": 5813978515, "lat": -9.9172829, "lon": 23.3504078}, {"type": "node", "id": 5813978516, "lat": -9.9172671, "lon": 23.3499706}, {"type": "node", "id": 5813978517, "lat": -9.9171746, "lon": 23.3495736}, {"type": "node", "id": 5813978518, "lat": -9.9170372, "lon": 23.3492491}, {"type": "node", "id": 5813978519, "lat": -9.9117661, "lon": 23.3411247}, {"type": "node", "id": 5813978520, "lat": -9.9104265, "lon": 23.3392686}, {"type": "node", "id": 5813978521, "lat": -9.9071291, "lon": 23.3351916}, {"type": "node", "id": 5813978522, "lat": -9.900896, "lon": 23.3275044}, {"type": "node", "id": 5813978523, "lat": -9.9007058, "lon": 23.3271209}, {"type": "node", "id": 5813978524, "lat": -9.8725724, "lon": 23.2623911}, {"type": "node", "id": 5813978525, "lat": -9.8723557, "lon": 23.2609803}, {"type": "node", "id": 5813978526, "lat": -9.8721443, "lon": 23.2595641}, {"type": "node", "id": 5813978527, "lat": -9.8668963, "lon": 23.2261437}, {"type": "node", "id": 5813978528, "lat": -9.8667536, "lon": 23.2248992}, {"type": "node", "id": 5813978529, "lat": -9.8667801, "lon": 23.2242287}, {"type": "node", "id": 5813978530, "lat": -9.866965, "lon": 23.2224155}, {"type": "node", "id": 5813978531, "lat": -9.8671077, "lon": 23.2209939}, {"type": "node", "id": 5813978532, "lat": -9.8673086, "lon": 23.2192719}, {"type": "node", "id": 5813978533, "lat": -9.867409, "lon": 23.2182473}, {"type": "node", "id": 5813978534, "lat": -9.8676151, "lon": 23.216477}, {"type": "node", "id": 5813978535, "lat": -9.8677154, "lon": 23.2153881}, {"type": "node", "id": 5813978536, "lat": -9.8678264, "lon": 23.214519}, {"type": "node", "id": 5813978537, "lat": -9.867948, "lon": 23.2131887}, {"type": "node", "id": 5813978538, "lat": -9.868133, "lon": 23.2116812}, {"type": "node", "id": 5813978539, "lat": -9.8682651, "lon": 23.2108229}, {"type": "node", "id": 5813978540, "lat": -9.8683814, "lon": 23.2095569}, {"type": "node", "id": 5813978541, "lat": -9.8686219, "lon": 23.2076606}, {"type": "node", "id": 5813978542, "lat": -9.8687725, "lon": 23.2062417}, {"type": "node", "id": 5813978543, "lat": -9.869922, "lon": 23.1955665}, {"type": "node", "id": 5813978544, "lat": -9.8699114, "lon": 23.1951615}, {"type": "node", "id": 5813978545, "lat": -9.8694754, "lon": 23.1934181}, {"type": "node", "id": 5813978546, "lat": -9.8692296, "lon": 23.1929192}, {"type": "node", "id": 5813978547, "lat": -9.8690552, "lon": 23.1926322}, {"type": "node", "id": 5813978548, "lat": -9.8471137, "lon": 23.1654668}, {"type": "node", "id": 5813978549, "lat": -9.7795979, "lon": 23.1356513}, {"type": "node", "id": 5813978550, "lat": -9.7792939, "lon": 23.1353845}, {"type": "node", "id": 5813978551, "lat": -9.7791274, "lon": 23.1352611}, {"type": "node", "id": 5813978552, "lat": -9.7644848, "lon": 23.120914}, {"type": "node", "id": 5813995385, "lat": -10.3021479, "lon": 23.4910518}, {"type": "node", "id": 5813995387, "lat": -10.2619793, "lon": 23.5079285}, {"type": "node", "id": 5813995388, "lat": -10.0856514, "lon": 23.5092428}, {"type": "node", "id": 5813995389, "lat": -10.0812994, "lon": 23.5092536}, {"type": "node", "id": 5813995390, "lat": -10.0752044, "lon": 23.5091543}, {"type": "node", "id": 5813995391, "lat": -10.0770688, "lon": 23.5092777}, {"type": "node", "id": 5813995392, "lat": -10.0755107, "lon": 23.5091999}, {"type": "node", "id": 5813995393, "lat": -10.0542777, "lon": 23.503857}, {"type": "node", "id": 5813995394, "lat": -10.054003, "lon": 23.5037979}, {"type": "node", "id": 5813995395, "lat": -10.0537996, "lon": 23.5037872}, {"type": "node", "id": 5813995396, "lat": -10.0535593, "lon": 23.5038757}, {"type": "node", "id": 5813995397, "lat": -10.0531499, "lon": 23.5040528}, {"type": "node", "id": 5813995398, "lat": -10.0518796, "lon": 23.5045677}, {"type": "node", "id": 5813995399, "lat": -10.0498354, "lon": 23.5052007}, {"type": "node", "id": 5813995400, "lat": -10.0503003, "lon": 23.5051525}, {"type": "node", "id": 5813995401, "lat": -10.0486707, "lon": 23.5051793}, {"type": "node", "id": 5813995402, "lat": -10.0467956, "lon": 23.5050103}, {"type": "node", "id": 5813995403, "lat": -10.0463096, "lon": 23.5048761}, {"type": "node", "id": 5813995404, "lat": -10.0444556, "lon": 23.5040179}, {"type": "node", "id": 5813995405, "lat": -10.0460614, "lon": 23.5047555}, {"type": "node", "id": 5813995406, "lat": -10.0377511, "lon": 23.5002535}, {"type": "node", "id": 5813995407, "lat": -10.037516, "lon": 23.5002011}, {"type": "node", "id": 5813995408, "lat": -10.0373747, "lon": 23.5000201}, {"type": "node", "id": 5813995409, "lat": -10.0369178, "lon": 23.4980299}, {"type": "node", "id": 5813995410, "lat": -10.0369099, "lon": 23.4979159}, {"type": "node", "id": 5813995411, "lat": -10.0360911, "lon": 23.4869027}, {"type": "node", "id": 5813995412, "lat": -10.0360356, "lon": 23.4866895}, {"type": "node", "id": 5813995413, "lat": -10.0359749, "lon": 23.486558}, {"type": "node", "id": 5813995414, "lat": -10.0334684, "lon": 23.480908}, {"type": "node", "id": 5813995415, "lat": -10.0332413, "lon": 23.4803769}, {"type": "node", "id": 5813995416, "lat": -10.0328953, "lon": 23.4794515}, {"type": "node", "id": 5813995417, "lat": -10.0323036, "lon": 23.4776598}, {"type": "node", "id": 5813995418, "lat": -10.0306555, "lon": 23.4726736}, {"type": "node", "id": 5813995419, "lat": -10.0273051, "lon": 23.4634991}, {"type": "node", "id": 5813995420, "lat": -10.0275363, "lon": 23.4637311}, {"type": "node", "id": 5813995421, "lat": -10.0268575, "lon": 23.4631357}, {"type": "node", "id": 5813995422, "lat": -10.0264428, "lon": 23.4629238}, {"type": "node", "id": 5813995423, "lat": -9.9768813, "lon": 23.4640557}, {"type": "node", "id": 5813995424, "lat": -9.9777003, "lon": 23.4641146}, {"type": "node", "id": 5813995425, "lat": -9.9646608, "lon": 23.4630901}, {"type": "node", "id": 5813995426, "lat": -9.9651733, "lon": 23.4628003}, {"type": "node", "id": 5813995427, "lat": -9.9655167, "lon": 23.4627575}, {"type": "node", "id": 5813995428, "lat": -9.9658232, "lon": 23.4627199}, {"type": "node", "id": 5985145454, "lat": -10.2267585, "lon": 23.5082638}, {"type": "node", "id": 5985145455, "lat": -10.2106671, "lon": 23.5083818}, {"type": "node", "id": 5985145456, "lat": -10.2016919, "lon": 23.5084462}, {"type": "node", "id": 5985145457, "lat": -10.1839519, "lon": 23.5085428}, {"type": "node", "id": 5985145458, "lat": -10.1424386, "lon": 23.5087895}, {"type": "node", "id": 5985145459, "lat": -10.0937268, "lon": 23.5091436}, {"type": "node", "id": 5985145460, "lat": -10.0365242, "lon": 23.4916663}, {"type": "node", "id": 5985145461, "lat": -9.9772828, "lon": 23.464061}, {"type": "node", "id": 5985145462, "lat": -9.952535, "lon": 23.4699833}, {"type": "node", "id": 5985145463, "lat": -9.9403849, "lon": 23.4728506}, {"type": "node", "id": 5985145464, "lat": -9.9118903, "lon": 23.4529781}, {"type": "node", "id": 5985145465, "lat": -9.9085506, "lon": 23.4157491}, {"type": "node", "id": 5985145466, "lat": -9.9102416, "lon": 23.4080565}, {"type": "node", "id": 5985145467, "lat": -9.9116684, "lon": 23.3690357}, {"type": "node", "id": 5985145468, "lat": -9.9110025, "lon": 23.3399498}, {"type": "node", "id": 5985145469, "lat": -9.9023149, "lon": 23.3293927}, {"type": "node", "id": 5985145470, "lat": -9.9039954, "lon": 23.3314633}, {"type": "node", "id": 5985145471, "lat": -9.8931198, "lon": 23.309834}, {"type": "node", "id": 5985145472, "lat": -9.8909636, "lon": 23.3049202}, {"type": "node", "id": 5985145473, "lat": -9.886757, "lon": 23.2952857}, {"type": "node", "id": 5985145474, "lat": -9.8759019, "lon": 23.2706094}, {"type": "node", "id": 5985145475, "lat": -9.8730692, "lon": 23.264097}, {"type": "node", "id": 5985145476, "lat": -9.8727627, "lon": 23.2632708}, {"type": "node", "id": 5985145477, "lat": -9.8706592, "lon": 23.2501709}, {"type": "node", "id": 5985145478, "lat": -9.8686404, "lon": 23.2373392}, {"type": "node", "id": 5985145479, "lat": -9.8680907, "lon": 23.2338631}, {"type": "node", "id": 5985145480, "lat": -9.8667906, "lon": 23.2254517}, {"type": "node", "id": 5985145481, "lat": -9.8667483, "lon": 23.2245827}, {"type": "node", "id": 5985145482, "lat": -9.8668646, "lon": 23.2232845}, {"type": "node", "id": 5985145483, "lat": -9.822023, "lon": 23.1517982}, {"type": "node", "id": 5985145484, "lat": -9.8108275, "lon": 23.1456399}, {"type": "node", "id": 5985146585, "lat": -9.8102672, "lon": 23.1453073}, {"type": "node", "id": 5985146586, "lat": -9.795149, "lon": 23.1406188}, {"type": "node", "id": 5985146587, "lat": -9.7805904, "lon": 23.1361422}, {"type": "node", "id": 5985146588, "lat": -9.7717196, "lon": 23.1280982}, {"type": "node", "id": 5985146589, "lat": -9.7701653, "lon": 23.1265962}, {"type": "node", "id": 8687088738, "lat": -9.9137365, "lon": 23.392108}, {"type": "node", "id": 10255784898, "lat": -9.9124422, "lon": 23.3982172}, {"type": "node", "id": 10307451107, "lat": -9.9246412, "lon": 23.4662417}, {"type": "node", "id": 10308763664, "lat": -10.0405863, "lon": 23.0430669}, {"type": "node", "id": 10308763665, "lat": -10.0404543, "lon": 23.0391589}, {"type": "node", "id": 10308763666, "lat": -10.0403064, "lon": 23.0397087}, {"type": "node", "id": 10537129525, "lat": -9.7738175, "lon": 23.1301969}, {"type": "node", "id": 10537736081, "lat": -9.9111949, "lon": 23.403794}, {"type": "node", "id": 10537779636, "lat": -10.0313409, "lon": 23.4747473}, {"type": "node", "id": 10537838235, "lat": -9.869272, "lon": 23.2411932}, {"type": "node", "id": 10537838322, "lat": -9.8693753, "lon": 23.2418616}, {"type": "node", "id": 10537838323, "lat": -9.8686494, "lon": 23.2373934}, {"type": "node", "id": 10542605317, "lat": -9.9884729, "lon": 23.4638241}, {"type": "node", "id": 10542605322, "lat": -9.841907, "lon": 23.1626461}, {"type": "node", "id": 10542954653, "lat": -9.7752598, "lon": 23.1315724}, {"type": "node", "id": 10542954686, "lat": -10.024124, "lon": 23.4628917}, {"type": "node", "id": 10542961272, "lat": -10.0432188, "lon": 23.5033235}, {"type": "node", "id": 10690403324, "lat": -9.8623404, "lon": 23.1842199}, {"type": "node", "id": 10690409846, "lat": -9.8675014, "lon": 23.1906568}, {"type": "node", "id": 10690409847, "lat": -9.8672542, "lon": 23.1903807}, {"type": "node", "id": 10690410037, "lat": -9.8683449, "lon": 23.1916877}, {"type": "node", "id": 10690512483, "lat": -9.8673957, "lon": 23.1905387}, {"type": "node", "id": 10690512484, "lat": -9.8698929, "lon": 23.196111}, {"type": "node", "id": 10690512485, "lat": -9.8697344, "lon": 23.1975514}, {"type": "node", "id": 10690512486, "lat": -9.8695018, "lon": 23.1996247}, {"type": "node", "id": 10690512487, "lat": -9.8698771, "lon": 23.1947699}, {"type": "node", "id": 10690512488, "lat": -9.8697529, "lon": 23.1941664}, {"type": "node", "id": 10690512489, "lat": -9.8696524, "lon": 23.1938687}, {"type": "way", "id": 33659589, "nodes": [436063202, 10308763665, 10308763666, 435331923, 10308763664, 435526326, 436104387, 435486093, 435991931, 435861857, 435977775, 435941937, 436070104, 436032890, 435576795, 435741299, 435746596, 435603811, 435624886, 435543947, 435261665, 435660840, 435794869, 435467162, 435300862, 435546520, 435274395, 435470382, 436066660, 435677433, 436083700, 435354074, 435840219, 382774935, 4983388668, 4983388667, 382476148, 4983388669, 4983388670, 382067527, 4983388672, 4983388671, 382099457, 4983388674, 4983388673, 382759310, 4983388675, 383798488, 4983388677, 4983388676, 435316858, 4983388678, 4983388680, 382474886, 4983388679, 435836898, 4983388681, 4983388682, 4983388683, 4983388685, 4983388684, 383811255, 4983388686, 4983388687, 435834403, 4983388689, 4983388688, 4983388691, 4983388690, 4983388693, 4983388692, 4983388694, 436044015, 4983388695, 436044948, 4983388696, 383608419, 4983388698, 4983388699, 4983388697, 4983388702, 435490387, 4983388701, 4983388700, 382446854, 435976833, 382122684, 4983388703, 435470557, 382494580, 4983388705, 435594225, 4983388704, 4983388706, 4983388707, 435890315, 4983388708, 435376772, 4983388709, 4983388710, 4983388711, 436045125, 4983388712, 4983388713, 382128922, 4983388714, 435992689, 382484793, 4983388715, 382127496, 4983388716, 4983388717, 4983388718, 4983388719, 435956762, 4983389122, 4983389121, 4983388720, 383610588, 4983389123, 381396476, 382459243, 4983389126, 4983389125, 4983389124, 435351018, 436017553, 435848095, 436087113, 382188149, 4983389129, 4983389128, 383829057, 4983389127, 435432691, 4983389133, 4983389132, 4983389130, 4983389131, 435929759, 435377296, 4983389134, 436070452, 382463373, 4983389138, 4983389137, 382155958, 4983389136, 4983389135, 381240602, 4983389139, 435647091, 4983389141, 4983389140, 383810869, 435792977, 4983389142, 382114657, 4983389143, 381333109, 4983389144, 383718087, 4983389145, 4983389147, 4983389146, 4983389148, 4983389149, 435840285, 4983389150, 382449537, 4983389152, 4983389151, 382793318, 4983389156, 435825380, 4983389155, 383781997, 4983389154, 382141044, 4983389153, 435359293, 4983389157, 4983389158, 435458011, 4983389159, 4983389160, 435528085, 4983389164, 4983389165, 382446088, 4983389163, 4983389162, 4983389161, 4983389166, 382081484, 4983389168, 4983389167, 4983389169, 4983389171, 4983389170, 435528646, 4983389172, 4983389173, 382104160, 4983389174, 4983389175, 4983389178, 4983389177, 4983389176, 4983389183, 4983389181, 4983389182, 435341614, 4983389180, 4983389179, 4983389184, 4983389185, 435722928, 382184253, 4983389186, 383844301, 435697397, 4983389187, 4983389188, 4983389189, 435676243, 4983389190, 4983389193, 4983389192, 4983389191, 4983389195, 4983389194, 435493709, 4983389198, 4983389197, 4983389196, 4983389200, 435319011, 4983389199, 4983389202, 4983389201, 4983389204, 4983389203, 435362649, 4983389205, 4983389206, 435951598, 4983389207, 381351109, 4983389208, 4983389210, 4983389209, 382493441, 4983389213, 4983389212, 4983389211, 383677077, 4983389214, 4983389216, 4983389215, 436004445, 4983389217, 4983389218, 4983389220, 4983389219, 383684582, 4983389221, 435474372, 4983389222, 382158118, 4983389223, 4983389224, 435377244, 4983389228, 4983389227, 4983389226, 4983389225, 4983389229, 4983389235, 4983389234, 4983389231, 4983389233, 4983389230, 4983389232, 4983389237, 4983389236, 382197047], "tags": {"ID": "5752", "highway": "unclassified"}}, {"type": "way", "id": 33670305, "nodes": [4983389238, 4983389274, 4983389273, 4983389272, 4983389271, 4983389270, 4983389269, 4983389268, 382103416, 4983389267, 4983389266, 383863480, 4983389264, 4983389265, 4983389263, 4983389262, 382486670, 4983389261, 382447916, 4983389260, 4983389256, 4983389257, 4983389258, 4983389259, 381249007, 4983389254, 4983389255, 4983389253, 4983389252, 435889717, 4983389251, 4983389250, 435999527, 4983389249, 4983389248, 4983389247, 435641950, 4983389246, 435478458, 4983389245, 435346556, 4983389244, 382126961, 4983389241, 4983389242, 4983389240, 435538570, 4983389239, 4983389243, 383865138], "tags": {"ID": "5736", "highway": "unclassified"}}, {"type": "way", "id": 49133250, "nodes": [5813995385, 4697407617, 4697407618, 4697407619, 4697407620, 4697407621, 435911614, 4697407622, 4697407623, 4697407624, 4697407625, 4697407626, 4697407627, 4697407628, 4697407629, 4697407630, 4697407631, 435906539, 4697407633, 5813995387, 4697407632, 4697407634, 4697407635, 4697407636, 4697428333, 5985145454, 435900021, 5985145455, 5985145456, 5985145457, 435895051, 5985145458, 382197047, 4983389238, 380941751, 5985145459, 5813995388, 5813995389, 435832384, 5813995391, 5813995392, 5813995390, 435748221, 5813995393, 5813995394, 5813995395, 5813995396, 5813995397, 5813995398, 435819852, 5813995400, 5813995399, 5813995401, 5813995402, 435837417, 5813995403, 5813995405, 5813995404, 10542961272, 5813995406, 5813995407, 435756911, 5813995408, 2671728711, 5813995409, 5813995410, 5985145460, 435783438, 5813995411, 5813995412, 5813995413, 5813995414, 5813995415, 5813995416, 5813995417, 10537779636, 5813995418, 435740918, 435763861, 5813995420, 5813995419, 5813995421, 5813995422, 435664232, 10542954686, 435802167, 10542605317, 435915735, 5813995424, 5985145461, 5813995423, 436062697, 435387835, 5813995428, 5813995427, 5813995426, 5813995425, 436065796, 435822576, 435473548, 5985145462, 5813978460, 435274897, 5813978461, 435847670, 5985145463, 435939510, 5813978463, 5813978462, 5813978464, 5813978465, 5813978466, 5813978467, 5813978468, 435274224, 435691989, 5813978470, 5813978469, 5813978471, 5813978472, 10307451107, 435784033, 5813978473, 435800629, 5813978476, 5813978475, 5813978474, 5813978477, 435840161, 5813978478, 5813978479, 5813978480, 435852897, 5985145464, 435798739, 5813978481, 97410714, 5813978482, 5813978483, 5813978484, 97410713, 5813978485, 5813978486, 5813978487, 5813978488, 5813978489, 5813978490, 5813978491, 5813978492, 5985145465, 5985145466, 10537736081, 10255784898, 5813978493, 5813978494, 8687088738, 5813978495, 435751980, 5813978496, 5813978497, 5813978498, 5813978499, 435778101, 5813978500, 5985145467, 97410709, 5813978502, 5813978503, 5813978504, 5813978505, 5813978506, 5813978507, 435783712, 5813978508, 5813978509, 5813978510, 5813978511, 5813978501, 435886250, 5813978512, 5813978513, 5813978514, 5813978515, 5813978516, 5813978517, 5813978518, 97410706, 435899080, 5813978519, 5985145468, 5813978520, 5813978521, 5985145470, 5985145469, 97410704, 5813978522, 5813978523, 436028211, 5985145471, 5985145472, 5985145473, 435742067, 5985145474, 436022886, 5985145475, 5985145476, 5813978524, 5813978525, 5813978526, 5985145477, 10537838322, 10537838235, 436087644, 10537838323, 5985145478, 5985145479, 97410699, 5813978527, 5985145480, 5813978528, 5985145481, 5813978529, 5985145482, 5813978530, 5813978531, 436017972, 5813978532, 5813978533, 5813978534, 5813978535, 5813978536, 5813978537, 5813978538, 5813978539, 5813978540, 5813978541, 5813978542, 97410695, 10690512486, 10690512485, 10690512484, 5813978543, 5813978544, 10690512487, 2275430119, 10690512488, 10690512489, 5813978545, 5813978546, 5813978547, 97410694, 10690410037, 10690409846, 10690512483, 10690409847, 10690403324, 97410693, 2275430118, 5813978548, 2275430114, 10542605322, 97410692, 2275430105, 435551240, 5985145483, 97410691, 5985145484, 5985146585, 97410690, 5985146586, 97410689, 5985146587, 5813978549, 97410688, 5813978550, 5813978551, 10542954653, 10537129525, 2275430051, 5985146588, 5985146589, 435951037, 2275430032, 5813978552], "tags": {"highway": "secondary", "ref": "RP607", "source": "Bing", "source:date": "2018/10/15"}}]}